multiseek/__init__.py
multiseek/logic.py
multiseek/models.py
multiseek/urls.py
multiseek/util.py
multiseek/views.py
multiseek/locale/es/LC_MESSAGES/django.mo
multiseek/locale/es/LC_MESSAGES/django.po
multiseek/locale/es/LC_MESSAGES/djangojs.mo
multiseek/locale/es/LC_MESSAGES/djangojs.po
multiseek/locale/pl/LC_MESSAGES/django.mo
multiseek/locale/pl/LC_MESSAGES/django.po
multiseek/locale/pl/LC_MESSAGES/djangojs.mo
multiseek/locale/pl/LC_MESSAGES/djangojs.po
multiseek/migrations/0001_initial.py
multiseek/migrations/__init__.py
multiseek/static/multiseek/css/style.css
multiseek/static/multiseek/js/multiseek.js
multiseek/templates/multiseek/base.html
multiseek/templates/multiseek/index.html
multiseek/templates/multiseek/multiseek_buttons.html
multiseek/templates/multiseek/multiseek_fields.html
multiseek/templates/multiseek/multiseek_head.html
multiseek/templates/multiseek/multiseek_ordering.html
multiseek/templates/multiseek/multiseek_report_types.html
multiseek/templates/multiseek/multiseek_results_frame.html
multiseek/templates/multiseek/results.html
multiseek/tests/__init__.py
multiseek/tests/test_logic.py
multiseek/tests/test_models.py
multiseek/tests/test_views.py
django_multiseek-0.9.47.dist-info/AUTHORS.txt
django_multiseek-0.9.47.dist-info/LICENSE
django_multiseek-0.9.47.dist-info/METADATA
django_multiseek-0.9.47.dist-info/WHEEL
django_multiseek-0.9.47.dist-info/top_level.txt
django_multiseek-0.9.47.dist-info/RECORD
