Metadata-Version: 2.1
Name: django-multiseek
Version: 0.9.47
Summary: Build a form to seek records using multiple parameters
Home-page: http://TODO
Author: Michał Pasternak
Author-email: michal.dtz@gmail.com
License: MIT
Keywords: django multiseek
Classifier: Development Status :: 4 - Beta
Classifier: Environment :: Web Environment
Classifier: Framework :: Django
Classifier: Intended Audience :: Developers
Classifier: License :: OSI Approved :: MIT License
Classifier: Operating System :: OS Independent
Classifier: Programming Language :: Python
Classifier: Programming Language :: Python :: 3
Classifier: Programming Language :: Python :: 3.8
Classifier: Programming Language :: Python :: 3.9
Classifier: Topic :: Internet :: WWW/HTTP
Classifier: Topic :: Software Development :: Libraries :: Python Modules
License-File: LICENSE
License-File: AUTHORS.txt
Requires-Dist: Django (>=1.11)
Requires-Dist: python-dateutil (>=2.8.1)
Requires-Dist: django-autocomplete-light (>=3.8.1)
